Metadata-Version: 2.1
Name: llogaritestax
Version: 1.0.0
Summary: A package calculates tax
Author: Flauranc Shehu
Author-email: <mail@gmail.com>
Keywords: tax,SDA,calculator,salary,Python,pack
Classifier: Development Status :: 1 - Planning
Classifier: Intended Audience :: Developers
Classifier: Programming Language :: Python :: 3
Classifier: Operating System :: Unix
Classifier: Operating System :: MacOS :: MacOS X
Classifier: Operating System :: Microsoft :: Windows
